Annotate/__init__.py
Annotate/main.py
AutoNotater-0.1.2.dist-info/METADATA
AutoNotater-0.1.2.dist-info/WHEEL
AutoNotater-0.1.2.dist-info/entry_points.txt
AutoNotater-0.1.2.dist-info/top_level.txt
AutoNotater-0.1.2.dist-info/RECORD
